genie_parser-0.1.0.data/scripts/genie-datagen
genie_parser-0.1.0.data/scripts/genie-decoder
genie_parser-0.1.0.data/scripts/genie-evaluator
genie_parser-0.1.0.data/scripts/genie-print-metrics
genie_parser-0.1.0.data/scripts/genie-server
genie_parser-0.1.0.data/scripts/genie-trainer
genieparser/__init__.py
genieparser/grammar/__init__.py
genieparser/grammar/abstract.py
genieparser/grammar/django.py
genieparser/grammar/ifttt.py
genieparser/grammar/posthingtalk.py
genieparser/grammar/shift_reduce_grammar.py
genieparser/grammar/simple.py
genieparser/grammar/thingtalk.py
genieparser/grammar/slr/__init__.py
genieparser/grammar/slr/generator.py
genieparser/grammar/slr/np_parser.py
genieparser/layers/__init__.py
genieparser/layers/common.py
genieparser/layers/hparams.py
genieparser/layers/modalities.py
genieparser/models/__init__.py
genieparser/models/base_model.py
genieparser/models/copy_seq2seq.py
genieparser/models/copy_transformer.py
genieparser/models/transformer.py
genieparser/scripts/__init__.py
genieparser/scripts/avg_checkpoints.py
genieparser/scripts/post_process_decoded_results.py
genieparser/scripts/process_logs.py
genieparser/scripts/retrieval.py
genieparser/scripts/utils/__init__.py
genieparser/scripts/utils/loader.py
genieparser/server/__init__.py
genieparser/server/admin_handlers.py
genieparser/server/application.py
genieparser/server/config.py
genieparser/server/constants.py
genieparser/server/exact.py
genieparser/server/learn_handler.py
genieparser/server/main.py
genieparser/server/predictor.py
genieparser/server/query_handlers.py
genieparser/server/tokenizer.py
genieparser/tasks/__init__.py
genieparser/tasks/base_problem.py
genieparser/tasks/semantic_parsing.py
genieparser/tasks/thingtalk.py
genieparser/util/__init__.py
genieparser/util/eval.py
genieparser/util/loader.py
genieparser/util/metrics.py
genieparser/util/strings.py
genieparser/util/trie.py
genie_parser-0.1.0.dist-info/COPYING
genie_parser-0.1.0.dist-info/LICENSE
genie_parser-0.1.0.dist-info/METADATA
genie_parser-0.1.0.dist-info/WHEEL
genie_parser-0.1.0.dist-info/top_level.txt
genie_parser-0.1.0.dist-info/RECORD
