Metadata-Version: 2.1
Name: genie-parser
Version: 0.1.0
Summary: UNKNOWN
Home-page: https://github.com/Stanford-Mobisocial-IoT-Lab/genie-parser
Author: Stanford Mobisocial Lab
Author-email: mobisocial@lists.stanford.edu
License: GPL-3.0+
Platform: UNKNOWN
Requires-Python: >=3.6
Requires-Dist: tensorflow (>=1.12.0)
Requires-Dist: tensor2tensor
Requires-Dist: orderedset
Requires-Dist: numpytornadoSQLAlchemysemver
